jupyterlab_skip_traceback/__init__.py
jupyterlab_skip_traceback/_version.py
jupyterlab_skip_traceback/labextension/build_log.json
jupyterlab_skip_traceback/labextension/package.json
jupyterlab_skip_traceback/labextension/schemas/jupyterlab-skip-traceback/package.json.orig
jupyterlab_skip_traceback/labextension/schemas/jupyterlab-skip-traceback/settings.json
jupyterlab_skip_traceback/labextension/static/lib_index_js-webpack_sharing_consume_default_lumino_coreutils.371c87394cdfe635f1e1.js
jupyterlab_skip_traceback/labextension/static/lib_index_js-webpack_sharing_consume_default_lumino_coreutils.371c87394cdfe635f1e1.js.map
jupyterlab_skip_traceback/labextension/static/remoteEntry.217eca687dd8591103fd.js
jupyterlab_skip_traceback/labextension/static/remoteEntry.217eca687dd8591103fd.js.map
jupyterlab_skip_traceback/labextension/static/style.js
jupyterlab_skip_traceback/labextension/static/style_index_js.769fb9da0a3e80a1dabc.js
jupyterlab_skip_traceback/labextension/static/style_index_js.769fb9da0a3e80a1dabc.js.map
jupyterlab_skip_traceback/labextension/static/vendors-node_modules_jupyterlab_apputils_lib_clipboard_js-node_modules_css-loader_dist_runtim-04500f.eed2a1fd11a98937e296.js
jupyterlab_skip_traceback/labextension/static/vendors-node_modules_jupyterlab_apputils_lib_clipboard_js-node_modules_css-loader_dist_runtim-04500f.eed2a1fd11a98937e296.js.map
jupyterlab_skip_traceback-5.1.0.data/data/share/jupyter/labextensions/jupyterlab-skip-traceback/build_log.json
jupyterlab_skip_traceback-5.1.0.data/data/share/jupyter/labextensions/jupyterlab-skip-traceback/package.json
jupyterlab_skip_traceback-5.1.0.data/data/share/jupyter/labextensions/jupyterlab-skip-traceback/schemas/jupyterlab-skip-traceback/package.json.orig
jupyterlab_skip_traceback-5.1.0.data/data/share/jupyter/labextensions/jupyterlab-skip-traceback/schemas/jupyterlab-skip-traceback/settings.json
jupyterlab_skip_traceback-5.1.0.dist-info/METADATA
jupyterlab_skip_traceback-5.1.0.dist-info/WHEEL
jupyterlab_skip_traceback-5.1.0.dist-info/licenses/LICENSE.txt
jupyterlab_skip_traceback-5.1.0.dist-info/RECORD
