Metadata-Version: 2.1
Name: jupyterlab-skip-traceback
Version: 5.1.0
Summary: A JupyterLab extension for rendering Errors with a copy/paste button and expand/collapse
Project-URL: Homepage, https://github.com/deshaw/jupyterlab-skip-traceback
Project-URL: Bug Tracker, https://github.com/deshaw/jupyterlab-skip-traceback/issues
Project-URL: Repository, https://github.com/deshaw/jupyterlab-skip-traceback.git
Author: Marc Udoff
License: Copyright 2020 D. E. Shaw & Co., L.P.
License-File: LICENSE.txt
Classifier: Framework :: Jupyter
Classifier: Framework :: Jupyter :: JupyterLab
Classifier: Framework :: Jupyter :: JupyterLab :: 4
Classifier: Framework :: Jupyter :: JupyterLab :: Extensions
Classifier: Framework :: Jupyter :: JupyterLab :: Extensions :: Prebuilt
Classifier: License :: OSI Approved :: BSD License
Classifier: Programming Language :: Python
Classifier: Programming Language :: Python :: 3
Classifier: Programming Language :: Python :: 3.8
Classifier: Programming Language :: Python :: 3.9
Classifier: Programming Language :: Python :: 3.10
Classifier: Programming Language :: Python :: 3.11
Requires-Python: >=3.8
